docs/source/conf.py
spyrit/__init__.py
spyrit/core/__init__.py
spyrit/core/inverse.py
spyrit/core/meas.py
spyrit/core/nnet.py
spyrit/core/noise.py
spyrit/core/prep.py
spyrit/core/recon.py
spyrit/core/torch.py
spyrit/core/train.py
spyrit/core/warp.py
spyrit/dev/meas.py
spyrit/dev/prep.py
spyrit/dev/recon.py
spyrit/external/__init__.py
spyrit/external/drunet.py
spyrit/hadamard_matrix/__init__.py
spyrit/hadamard_matrix/create_hadamard_matrix_with_sage.py
spyrit/hadamard_matrix/download_hadamard_matrix.py
spyrit/misc/__init__.py
spyrit/misc/color.py
spyrit/misc/data_visualisation.py
spyrit/misc/disp.py
spyrit/misc/examples.py
spyrit/misc/load_data.py
spyrit/misc/matrix_tools.py
spyrit/misc/metrics.py
spyrit/misc/pattern_choice.py
spyrit/misc/sampling.py
spyrit/misc/statistics.py
spyrit/misc/walsh_hadamard.py
spyrit-3.0.2.data/scripts/tuto_01_a_acquisition_operators.py
spyrit-3.0.2.data/scripts/tuto_01_b_splitting.py
spyrit-3.0.2.data/scripts/tuto_01_c_HadamSplit2d.py
spyrit-3.0.2.data/scripts/tuto_02_noise.py
spyrit-3.0.2.data/scripts/tuto_03_pseudoinverse_linear.py
spyrit-3.0.2.dist-info/licenses/AUTHORS
spyrit-3.0.2.dist-info/licenses/LICENSE.md
tutorial/tuto_01_a_acquisition_operators.py
tutorial/tuto_01_b_splitting.py
tutorial/tuto_01_c_HadamSplit2d.py
tutorial/tuto_02_noise.py
tutorial/tuto_03_pseudoinverse_linear.py
tutorial/tuto_04_b_train_pseudoinverse_cnn_linear.py
tutorial/tuto_04_pseudoinverse_cnn_linear.py
tutorial/tuto_05_dcnet.py
tutorial/wip/_tuto_04_train_pseudoinverse_cnn_linear.py
tutorial/wip/_tuto_05_recon_hadamSplit.py
tutorial/wip/_tuto_06_dcnet_split_measurements.py
tutorial/wip/_tuto_07_drunet_split_measurements.py
tutorial/wip/_tuto_08_lpgd_split_measurements.py
tutorial/wip/_tuto_09_dynamic.py
tutorial/wip/_tuto_bonus_advanced_methods_colab.py
spyrit-3.0.2.dist-info/METADATA
spyrit-3.0.2.dist-info/WHEEL
spyrit-3.0.2.dist-info/top_level.txt
spyrit-3.0.2.dist-info/RECORD
