Metadata-Version: 2.4
Name: spyrit
Version: 3.0.2
Summary: Toolbox for deep image reconstruction
Author-email: Nicolas Ducros <Nicolas.Ducros@insa-lyon.fr>
License:                    GNU LESSER GENERAL PUBLIC LICENSE
Classifier: Programming Language :: Python
Classifier: Programming Language :: Python :: 3.9
Classifier: Programming Language :: Python :: 3.10
Classifier: Programming Language :: Python :: 3.11
Classifier: Programming Language :: Python :: Implementation :: PyPy
Classifier: Operating System :: OS Independent
Requires-Python: >=3.9
License-File: LICENSE.md
License-File: AUTHORS
Requires-Dist: numpy
Requires-Dist: matplotlib
Requires-Dist: scipy
Requires-Dist: torch
Requires-Dist: torchvision
Requires-Dist: Pillow
Requires-Dist: PyWavelets
Requires-Dist: wget
Requires-Dist: sympy
Requires-Dist: imageio
Requires-Dist: astropy
Requires-Dist: requests
Requires-Dist: tqdm
Requires-Dist: girder-client
Dynamic: license-file
